{
  "title": "홍)cctv2",
  "customerName": "",
  "date": "[25.09.09]",
  "timestamp": 1757384644338,
  "selectedOptions": {
    "cctv": [
      {
        "label": "구매형 200만",
        "quantity": 2,
        "unitPrice": 27500,
        "basePrice": 27500,
        "prices": {
          "2": 33000,
          "3": 38500,
          "4": 44000,
          "5": 55000,
          "6": 60500,
          "7": 66000,
          "8": 71500
        },
        "price": 33000,
        "oneTimePayment": 0,
        "benefits": {
          "oneTimePayment": 0
        }
      }
    ],
    "manual_discount": []
  },
  "manualInputs": {},
  "selectedExtraBenefit": "",
  "customGiftCard": 0,
  "customCash": 0,
  "isCardDiscountApplied": false,
  "isBusiness": false,
  "showSticker": true,
  "stickerText": "<필수 숙지 사항>\n■ 구매형 CCTV 2대 200만화소 / 저장기간 약30일 / 구매형은 3년후 납입요금 없음 (무상A/S 개통 후 1년)\n■ 본 견적서는 고객님께만 제공되는 전용자료로, 외부 공유 시 법적 책임이 발생할 수 있으니 유의 부탁드립니다.\n■ 사은품은 서비스개통후 익주 금요일 18시 이전에 정산후 문자안내 드립니다.\n■ CCTV 난공사시 청구 : 층간공사, 벽타공, 선로길이 30M 이상 , 층고 3M 이상\n☎ 대표번호 1899-6484 (문자가능)",
  "excludedCombos": [],
  "originalTotal": 33000,
  "discountTotal": 0,
  "finalTotal": 33000,
  "productBenefits": {
    "giftCard": 0,
    "cash": 30000,
    "items": [
      "CCTV 현금사은품 30,000원"
    ],
    "productBenefits": [
      {
        "title": "CCTV",
        "label": "구매형 200만",
        "service": "cctv",
        "giftCard": 0,
        "cash": 30000
      }
    ]
  },
  "extraBenefits": {
    "giftCard": 0,
    "cash": 0,
    "productBenefits": []
  },
  "comboDiscount": null,
  "cardDiscounts": null
}